LICENSE.md
gradle_bodyguard/__init__.py
gradle_bodyguard/app.py
gradle_bodyguard/cli_parser.py
gradle_bodyguard/constants.py
gradle_bodyguard/coordinates_translator.py
gradle_bodyguard/gradle_runner.py
gradle_bodyguard/gradle_scanner.py
gradle_bodyguard/gradlew_locator.py
gradle_bodyguard/ossindex_fetcher.py
gradle_bodyguard/report_generator.py
gradle_bodyguard/security_reporter.py
gradle_bodyguard/utils/__init__.py
gradle_bodyguard/utils/cli_colorizer.py
gradle_bodyguard/utils/dependencies_slicer.py
gradle_bodyguard/utils/logging.py
gradle_bodyguard/vulnerabilities_matcher.py
gradle_bodyguard-0.0.4.dist-info/entry_points.txt
gradle_bodyguard-0.0.4.dist-info/LICENSE.md
gradle_bodyguard-0.0.4.dist-info/WHEEL
gradle_bodyguard-0.0.4.dist-info/METADATA
gradle_bodyguard-0.0.4.dist-info/RECORD
