Metadata-Version: 2.1
Name: gradle-bodyguard
Version: 0.0.4
Summary: A tool that scans dependencies in your Gradle project and warns you about potential security issues
Home-page: https://github.com/dotanuki-labs/gradle-bodyguard
License: MIT
Keywords: gradle,cves,ossindex
Author: Ubiratan Soares
Author-email: ubiratan.f.soares@gmail.com
Requires-Python: >=3.8,<4.0
Classifier: Environment :: Console
Classifier: License :: OSI Approved :: MIT License
Classifier: Operating System :: OS Independent
Classifier: Programming Language :: Python :: 3
Classifier: Programming Language :: Python :: 3.8
Requires-Dist: flake8 (>=3.8.2,<4.0.0)
Requires-Dist: requests (>=2.23.0,<3.0.0)
Project-URL: Repository, https://github.com/dotanuki-labs/gradle-bodyguard
